l293d/__init__.py
l293d/config.py
l293d/driver.py
l293d-0.3.4.dist-info/LICENSE.txt
l293d-0.3.4.dist-info/METADATA
l293d-0.3.4.dist-info/WHEEL
l293d-0.3.4.dist-info/top_level.txt
l293d-0.3.4.dist-info/RECORD
