Metadata-Version: 2.1
Name: l293d
Version: 0.3.4
Summary: A Python module to drive motors using an L293D via Raspberry Pi GPIO
Home-page: https://github.com/jmsv/l293d
Author: James Vickery
Author-email: dev@jamesvickery.net
License: MIT
Download-URL: https://github.com/jmsv/l293d/archive/v0.3.4.tar.gz
Project-URL: Bug Reports, https://github.com/jmsv/l293d/issues
Project-URL: Source, https://github.com/jmsv/l293d
Keywords: raspberry,pi,gpio,l293d,chip,motor,driver
Platform: UNKNOWN
Classifier: Development Status :: 5 - Production/Stable
Classifier: License :: OSI Approved :: MIT License
Classifier: Programming Language :: Python
Classifier: Programming Language :: Python :: 2.7
Classifier: Programming Language :: Python :: 3
Classifier: Programming Language :: Python :: 3.4
Classifier: Programming Language :: Python :: 3.5
Classifier: Programming Language :: Python :: 3.6
Classifier: Programming Language :: Python :: 3.7
Classifier: Programming Language :: Python :: 3.8
Classifier: Programming Language :: Python :: 3.9
Classifier: Programming Language :: Python :: 3.10
Classifier: Intended Audience :: Developers
Classifier: Natural Language :: English
Classifier: Operating System :: POSIX :: Linux
Requires-Python: >=2.7, !=3.0.*, !=3.1.*, !=3.2.*, !=3.2.*, <4
